pybase64/__init__.py
pybase64/__main__.py
pybase64/_fallback.py
pybase64/_license.py
pybase64/_license.pyi
pybase64/_pybase64.cpython-313-arm-linux-musleabihf.so
pybase64/_pybase64.pyi
pybase64/_typing.py
pybase64/_version.py
pybase64/py.typed
pybase64-1.4.3.dist-info/METADATA
pybase64-1.4.3.dist-info/WHEEL
pybase64-1.4.3.dist-info/entry_points.txt
pybase64-1.4.3.dist-info/top_level.txt
pybase64-1.4.3.dist-info/RECORD
pybase64-1.4.3.dist-info/licenses/LICENSE
