Metadata-Version: 2.1
Name: pybase64
Version: 1.4.3
Summary: Fast Base64 encoding/decoding
Home-page: https://github.com/mayeut/pybase64
Author: Matthieu Darbois
License: BSD-2-Clause
Project-URL: Source, https://github.com/mayeut/pybase64
Project-URL: Tracker, https://github.com/mayeut/pybase64/issues
Project-URL: Documentation, https://pybase64.readthedocs.io/en/stable
Keywords: base64
Classifier: Development Status :: 5 - Production/Stable
Classifier: Intended Audience :: Developers
Classifier: Topic :: Software Development :: Libraries :: Python Modules
Classifier: Topic :: Utilities
Classifier: License :: OSI Approved :: BSD License
Classifier: Programming Language :: C
Classifier: Programming Language :: Python :: 3
Classifier: Programming Language :: Python :: 3.8
Classifier: Programming Language :: Python :: 3.9
Classifier: Programming Language :: Python :: 3.10
Classifier: Programming Language :: Python :: 3.11
Classifier: Programming Language :: Python :: 3.12
Classifier: Programming Language :: Python :: 3.13
Classifier: Programming Language :: Python :: 3.14
Requires-Python: >=3.8
License-File: LICENSE
